{
  "project_info": {
    "project_number": "388260576417",
    "project_id": "mvvm-ca8f0",
    "storage_bucket": "mvvm-ca8f0.firebasestorage.app"
  },
  "client": [
    {
      "client_info": {
        "mobilesdk_app_id": "1:388260576417:android:7a21854d55309849a8c4e0",
        "android_client_info": {
          "package_name": "com.cursokotlin.s12_mvvm"
        }
      },
      "oauth_client": [],
      "api_key": [
        {
          "current_key": "AIzaSyCZh_e6y_--DthNSvlBCrjIR3_3RECF0tY"
        }
      ],
      "services": {
        "appinvite_service": {
          "other_platform_oauth_client": []
        }
      }
    }
  ],
  "configuration_version": "1"
}